<content name="[ТРЕБУЕТ ПЕРЕВОД] Mobile Repair Service" id="ws_1683361083" author="Assailer" version="137" date="2022-06-15" save="0" description="[ТРЕБУЕТ ПЕРЕВОД] Мобильная Служба Ремонта" lastupdate="1655313191">
  <text language="7" name="[ТРЕБУЕТ ПЕРЕВОД] Mobile Repair Service" description="[ТРЕБУЕТ ПЕРЕВОД] Мобильная Служба Ремонта" />
  <text language="33" name="Mobile Repair Service" description="Mobile Repair Service" />
  <text language="34" name="Mobile Repair Service" description="Mobile Repair Service" />
  <text language="39" name="Mobile Repair Service" description="Mobile Repair Service" />
  <text language="44" name="Mobile Repair Service" description="Mobile Repair Service" />
  <text language="49" name="Mobiler Reparatur Service" description="Ein Spieler-kontrolliertes Schiff kann mit Reparaturen beauftragt werden.\n Schnelle Schiffe sind vorteilhaft." />
  <text language="86" name="Mobile Repair Service" description="Mobile Repair Service" />
  <text language="88" name="Mobile Repair Service" description="Mobile Repair Service" />
</content>